<?xml version="1.0" encoding="utf-8" ?><dwsync><file name="fontawesome-webfont.eot" server="indra.com//home/cust2/salmon/salmonroe.com/ToO_blocs/" local="3604995798" remote="3614191080" Dst="-1" /><file name="fontawesome-webfont.svg" server="indra.com//home/cust2/salmon/salmonroe.com/ToO_blocs/" local="3604995798" remote="3614191080" Dst="-1" /><file name="fontawesome-webfont.woff" server="indra.com//home/cust2/salmon/salmonroe.com/ToO_blocs/" local="3604995798" remote="3614191080" Dst="-1" /><file name="fontawesome-webfont.ttf" server="indra.com//home/cust2/salmon/salmonroe.com/ToO_blocs/" local="3604995798" remote="3614191080" Dst="-1" /><file name="fontawesome-webfont.woff2" server="indra.com//home/cust2/salmon/salmonroe.com/ToO_blocs/" local="3604995798" remote="3614191080" Dst="-1" /><file name="FontAwesome.otf" server="indra.com//home/cust2/salmon/salmonroe.com/ToO_blocs/" local="3604995798" remote="3614191080" Dst="-1" /><file name="LithosPro-Black.otf" server="indra.com//home/cust2/salmon/salmonroe.com/ToO_blocs/" local="3524092861" remote="3614191080" Dst="-1" /><file name="LithosPro-Bold.otf" server="indra.com//home/cust2/salmon/salmonroe.com/ToO_blocs/" local="3052145679" remote="3614191080" Dst="-1" /><file name="LithosPro-ExtraLight.otf" server="indra.com//home/cust2/salmon/salmonroe.com/ToO_blocs/" local="3052145686" remote="3614191080" Dst="-1" /><file name="LithosPro-Light.otf" server="indra.com//home/cust2/salmon/salmonroe.com/ToO_blocs/" local="3052145694" remote="3614191080" Dst="-1" /><file name="LithosPro-Regular.otf" server="indra.com//home/cust2/salmon/salmonroe.com/ToO_blocs/" local="3524092861" remote="3614191080" Dst="-1" /></dwsync>